<stg><name>dut</name>


<trans_list>

<trans id="114" from="1" to="2">
<condition id="49">
<or_exp><and_exp></and_exp></or_exp>
</condition>
</trans>

<trans id="115" from="2" to="3">
<condition id="50">
<or_exp><and_exp><literal name="p_Val2_5" val="4"/>
</and_exp><and_exp><literal name="p_Val2_5" val="5"/>
</and_exp><and_exp><literal name="p_Val2_5" val="!1"/>
<literal name="p_Val2_5" val="!2"/>
<literal name="p_Val2_5" val="!3"/>
</and_exp></or_exp>
</condition>
</trans>

<trans id="116" from="2" to="4">
<condition id="52">
<or_exp><and_exp><literal name="p_Val2_5" val="3"/>
</and_exp></or_exp>
</condition>
</trans>

<trans id="117" from="2" to="23">
<condition id="51">
<or_exp><and_exp><literal name="p_Val2_5" val="1"/>
</and_exp><and_exp><literal name="p_Val2_5" val="2"/>
</and_exp></or_exp>
</condition>
</trans>

<trans id="120" from="3" to="24">
<condition id="56">
<or_exp><and_exp><literal name="p_Val2_5" val="4"/>
</and_exp><and_exp><literal name="p_Val2_5" val="5"/>
</and_exp><and_exp><literal name="p_Val2_5" val="!1"/>
<literal name="p_Val2_5" val="!2"/>
<literal name="p_Val2_5" val="!3"/>
</and_exp></or_exp>
</condition>
</trans>

<trans id="165" from="4" to="24">
<condition id="87">
<or_exp><and_exp><literal name="exitcond_flatten" val="1"/>
</and_exp></or_exp>
</condition>
</trans>

<trans id="166" from="4" to="5">
<condition id="106">
<or_exp><and_exp><literal name="exitcond_flatten" val="0"/>
</and_exp></or_exp>
</condition>
</trans>

<trans id="147" from="5" to="6">
<condition id="88">
<or_exp><and_exp></and_exp></or_exp>
</condition>
</trans>

<trans id="148" from="6" to="7">
<condition id="89">
<or_exp><and_exp></and_exp></or_exp>
</condition>
</trans>

<trans id="149" from="7" to="8">
<condition id="90">
<or_exp><and_exp></and_exp></or_exp>
</condition>
</trans>

<trans id="150" from="8" to="9">
<condition id="91">
<or_exp><and_exp></and_exp></or_exp>
</condition>
</trans>

<trans id="151" from="9" to="10">
<condition id="92">
<or_exp><and_exp></and_exp></or_exp>
</condition>
</trans>

<trans id="152" from="10" to="11">
<condition id="93">
<or_exp><and_exp></and_exp></or_exp>
</condition>
</trans>

<trans id="153" from="11" to="12">
<condition id="94">
<or_exp><and_exp></and_exp></or_exp>
</condition>
</trans>

<trans id="154" from="12" to="13">
<condition id="95">
<or_exp><and_exp></and_exp></or_exp>
</condition>
</trans>

<trans id="155" from="13" to="14">
<condition id="96">
<or_exp><and_exp></and_exp></or_exp>
</condition>
</trans>

<trans id="156" from="14" to="15">
<condition id="97">
<or_exp><and_exp></and_exp></or_exp>
</condition>
</trans>

<trans id="157" from="15" to="16">
<condition id="98">
<or_exp><and_exp></and_exp></or_exp>
</condition>
</trans>

<trans id="158" from="16" to="17">
<condition id="99">
<or_exp><and_exp></and_exp></or_exp>
</condition>
</trans>

<trans id="159" from="17" to="18">
<condition id="100">
<or_exp><and_exp></and_exp></or_exp>
</condition>
</trans>

<trans id="160" from="18" to="19">
<condition id="101">
<or_exp><and_exp></and_exp></or_exp>
</condition>
</trans>

<trans id="161" from="19" to="20">
<condition id="102">
<or_exp><and_exp></and_exp></or_exp>
</condition>
</trans>

<trans id="162" from="20" to="21">
<condition id="103">
<or_exp><and_exp></and_exp></or_exp>
</condition>
</trans>

<trans id="163" from="21" to="22">
<condition id="104">
<or_exp><and_exp></and_exp></or_exp>
</condition>
</trans>

<trans id="164" from="22" to="4">
<condition id="105">
<or_exp><and_exp></and_exp></or_exp>
</condition>
</trans>

<trans id="142" from="23" to="24">
<condition id="81">
<or_exp><and_exp><literal name="p_Val2_5" val="1"/>
</and_exp><and_exp><literal name="p_Val2_5" val="2"/>
</and_exp></or_exp>
</condition>
</trans>
</trans_list>



<state_list>

<state id="1" st_id="1">

<operation id="25" st_id="1" stage="1" lat="1">
<core>FIFO</core>
<MemPortIdVec></MemPortIdVec>
<condition id="34">
<or_exp><and_exp></and_exp></or_exp>
</condition>

<node id="8" bw="32" op_0_bw="32" op_1_bw="32">
<![CDATA[
_ifconv:5  %tmp_128 = call float @_ssdm_op_Read.ap_fifo.volatile.floatP(float* %strm_in_V)

]]></node>
<StgValue><ssdm name="tmp_128"/></StgValue>
</operation>

<operation id="26" st_id="1" stage="1" lat="1">
<core>NULL</core>
<MemPortIdVec></MemPortIdVec>
<condition id="34">
<or_exp><and_exp></and_exp></or_exp>
</condition>

<node id="9" bw="32" op_0_bw="32">
<![CDATA[
_ifconv:6  %p_Val2_s = bitcast float %tmp_128 to i32

]]></node>
<StgValue><ssdm name="p_Val2_s"/></StgValue>
</operation>

<operation id="27" st_id="1" stage="1" lat="1">
<core>NULL</core>
<MemPortIdVec></MemPortIdVec>
<condition id="34">
<or_exp><and_exp></and_exp></or_exp>
</condition>

<node id="10" bw="1" op_0_bw="1" op_1_bw="32" op_2_bw="32">
<![CDATA[
_ifconv:7  %p_Result_s = call i1 @_ssdm_op_BitSelect.i1.i32.i32(i32 %p_Val2_s, i32 31)

]]></node>
<StgValue><ssdm name="p_Result_s"/></StgValue>
</operation>

<operation id="28" st_id="1" stage="1" lat="1">
<core>NULL</core>
<MemPortIdVec></MemPortIdVec>
<condition id="34">
<or_exp><and_exp></and_exp></or_exp>
</condition>

<node id="11" bw="8" op_0_bw="8" op_1_bw="32" op_2_bw="32" op_3_bw="32">
<![CDATA[
_ifconv:8  %loc_V = call i8 @_ssdm_op_PartSelect.i8.i32.i32.i32(i32 %p_Val2_s, i32 23, i32 30) nounwind

]]></node>
<StgValue><ssdm name="loc_V"/></StgValue>
</operation>

<operation id="29" st_id="1" stage="1" lat="1">
<core>NULL</core>
<MemPortIdVec></MemPortIdVec>
<condition id="34">
<or_exp><and_exp></and_exp></or_exp>
</condition>

<node id="12" bw="23" op_0_bw="32">
<![CDATA[
_ifconv:9  %loc_V_1 = trunc i32 %p_Val2_s to i23

]]></node>
<StgValue><ssdm name="loc_V_1"/></StgValue>
</operation>

<operation id="30" st_id="1" stage="1" lat="1">
<core>NULL</core>
<MemPortIdVec></MemPortIdVec>
<condition id="34">
<or_exp><and_exp></and_exp></or_exp>
</condition>

<node id="15" bw="9" op_0_bw="8">
<![CDATA[
_ifconv:12  %tmp_i_i_i_cast1 = zext i8 %loc_V to i9

]]></node>
<StgValue><ssdm name="tmp_i_i_i_cast1"/></StgValue>
</operation>

<operation id="31" st_id="1" stage="1" lat="1">
<core>AddSub</core>
<MemPortIdVec></MemPortIdVec>
<condition id="34">
<or_exp><and_exp></and_exp></or_exp>
</condition>

<node id="16" bw="9" op_0_bw="9" op_1_bw="9">
<![CDATA[
_ifconv:13  %sh_assign = add i9 -127, %tmp_i_i_i_cast1

]]></node>
<StgValue><ssdm name="sh_assign"/></StgValue>
</operation>

<operation id="32" st_id="1" stage="1" lat="1">
<core>NULL</core>
<MemPortIdVec></MemPortIdVec>
<condition id="34">
<or_exp><and_exp></and_exp></or_exp>
</condition>

<node id="17" bw="1" op_0_bw="1" op_1_bw="9" op_2_bw="32">
<![CDATA[
_ifconv:14  %isNeg = call i1 @_ssdm_op_BitSelect.i1.i9.i32(i9 %sh_assign, i32 8)

]]></node>
<StgValue><ssdm name="isNeg"/></StgValue>
</operation>

<operation id="33" st_id="1" stage="1" lat="1">
<core>AddSub</core>
<MemPortIdVec></MemPortIdVec>
<condition id="34">
<or_exp><and_exp></and_exp></or_exp>
</condition>

<node id="18" bw="8" op_0_bw="8" op_1_bw="8">
<![CDATA[
_ifconv:15  %tmp_17_i_i = sub i8 127, %loc_V

]]></node>
<StgValue><ssdm name="tmp_17_i_i"/></StgValue>
</operation>

<operation id="34" st_id="1" stage="1" lat="1">
<core>NULL</core>
<MemPortIdVec></MemPortIdVec>
<condition id="34">
<or_exp><and_exp></and_exp></or_exp>
</condition>

<node id="19" bw="9" op_0_bw="8">
<![CDATA[
_ifconv:16  %tmp_17_i_i_cast = sext i8 %tmp_17_i_i to i9

]]></node>
<StgValue><ssdm name="tmp_17_i_i_cast"/></StgValue>
</operation>

<operation id="35" st_id="1" stage="1" lat="1">
<core>Sel</core>
<MemPortIdVec></MemPortIdVec>
<condition id="34">
<or_exp><and_exp></and_exp></or_exp>
</condition>

<node id="20" bw="9" op_0_bw="1" op_1_bw="9" op_2_bw="9">
<![CDATA[
_ifconv:17  %sh_assign_1 = select i1 %isNeg, i9 %tmp_17_i_i_cast, i9 %sh_assign

]]></node>
<StgValue><ssdm name="sh_assign_1"/></StgValue>
</operation>
</state>

<state id="2" st_id="2">

<operation id="36" st_id="2" stage="1" lat="1">
<core>NULL</core>
<MemPortIdVec></MemPortIdVec>
<condition id="35">
<or_exp><and_exp></and_exp></or_exp>
</condition>

<node id="3" bw="32" op_0_bw="32" op_1_bw="32" op_2_bw="0" op_3_bw="32" op_4_bw="32" op_5_bw="32" op_6_bw="32" op_7_bw="0" op_8_bw="0" op_9_bw="0" op_10_bw="32" op_11_bw="32" op_12_bw="32" op_13_bw="32" op_14_bw="0">
<![CDATA[
_ifconv:0  %empty = call i32 (...)* @_ssdm_op_SpecInterface(float* %strm_out_V, [8 x i8]* @ap_fifo_str, i32 0, i32 0, i32 0, i32 0, [1 x i8]* @p_str, [1 x i8]* @p_str, [1 x i8]* @p_str, i32 2, i32 2, i32 16, i32 16, [1 x i8]* @p_str)

]]></node>
<StgValue><ssdm name="empty"/></StgValue>
</operation>

<operation id="37" st_id="2" stage="1" lat="1">
<core>NULL</core>
<MemPortIdVec></MemPortIdVec>
<condition id="35">
<or_exp><and_exp></and_exp></or_exp>
</condition>

<node id="4" bw="32" op_0_bw="32" op_1_bw="32" op_2_bw="0" op_3_bw="32" op_4_bw="32" op_5_bw="32" op_6_bw="32" op_7_bw="0" op_8_bw="0" op_9_bw="0" op_10_bw="32" op_11_bw="32" op_12_bw="32" op_13_bw="32" op_14_bw="0">
<![CDATA[
_ifconv:1  %empty_18 = call i32 (...)* @_ssdm_op_SpecInterface(float* %strm_in_V, [8 x i8]* @ap_fifo_str, i32 0, i32 0, i32 0, i32 0, [1 x i8]* @p_str, [1 x i8]* @p_str, [1 x i8]* @p_str, i32 2, i32 2, i32 16, i32 16, [1 x i8]* @p_str)

]]></node>
<StgValue><ssdm name="empty_18"/></StgValue>
</operation>

<operation id="38" st_id="2" stage="1" lat="1">
<core>NULL</core>
<MemPortIdVec></MemPortIdVec>
<condition id="35">
<or_exp><and_exp></and_exp></or_exp>
</condition>

<node id="5" bw="0" op_0_bw="0" op_1_bw="32">
<![CDATA[
_ifconv:2  call void (...)* @_ssdm_op_SpecBitsMap(float* %strm_in_V), !map !212

]]></node>
<StgValue><ssdm name=""/></StgValue>
</operation>

<operation id="39" st_id="2" stage="1" lat="1">
<core>NULL</core>
<MemPortIdVec></MemPortIdVec>
<condition id="35">
<or_exp><and_exp></and_exp></or_exp>
</condition>

<node id="6" bw="0" op_0_bw="0" op_1_bw="32">
<![CDATA[
_ifconv:3  call void (...)* @_ssdm_op_SpecBitsMap(float* %strm_out_V), !map !218

]]></node>
<StgValue><ssdm name=""/></StgValue>
</operation>

<operation id="40" st_id="2" stage="1" lat="1">
<core>NULL</core>
<MemPortIdVec></MemPortIdVec>
<condition id="35">
<or_exp><and_exp></and_exp></or_exp>
</condition>

<node id="7" bw="0" op_0_bw="0" op_1_bw="0">
<![CDATA[
_ifconv:4  call void (...)* @_ssdm_op_SpecTopModule([4 x i8]* @dut_str) nounwind

]]></node>
<StgValue><ssdm name=""/></StgValue>
</operation>

<operation id="41" st_id="2" stage="1" lat="1">
<core>NULL</core>
<MemPortIdVec></MemPortIdVec>
<condition id="35">
<or_exp><and_exp></and_exp></or_exp>
</condition>

<node id="13" bw="24" op_0_bw="24" op_1_bw="1" op_2_bw="23">
<![CDATA[
_ifconv:10  %p_Result_1 = call i24 @_ssdm_op_BitConcatenate.i24.i1.i23(i1 true, i23 %loc_V_1) nounwind

]]></node>
<StgValue><ssdm name="p_Result_1"/></StgValue>
</operation>

<operation id="42" st_id="2" stage="1" lat="1">
<core>NULL</core>
<MemPortIdVec></MemPortIdVec>
<condition id="115">
<or_exp><and_exp><literal name="isNeg" val="0"/>
</and_exp></or_exp>
</condition>

<node id="14" bw="78" op_0_bw="24">
<![CDATA[
_ifconv:11  %tmp_i_i = zext i24 %p_Result_1 to i78

]]></node>
<StgValue><ssdm name="tmp_i_i"/></StgValue>
</operation>

<operation id="43" st_id="2" stage="1" lat="1">
<core>NULL</core>
<MemPortIdVec></MemPortIdVec>
<condition id="117">
<or_exp><and_exp><literal name="isNeg" val="0"/>
</and_exp></or_exp>
</condition>

<node id="21" bw="32" op_0_bw="9">
<![CDATA[
_ifconv:18  %sh_assign_1_cast = sext i9 %sh_assign_1 to i32

]]></node>
<StgValue><ssdm name="sh_assign_1_cast"/></StgValue>
</operation>

<operation id="44" st_id="2" stage="1" lat="1">
<core>NULL</core>
<MemPortIdVec></MemPortIdVec>
<condition id="112">
<or_exp><and_exp><literal name="isNeg" val="1"/>
</and_exp></or_exp>
</condition>

<node id="22" bw="24" op_0_bw="9">
<![CDATA[
_ifconv:19  %sh_assign_1_cast_cast = sext i9 %sh_assign_1 to i24

]]></node>
<StgValue><ssdm name="sh_assign_1_cast_cast"/></StgValue>
</operation>

<operation id="45" st_id="2" stage="1" lat="1">
<core>NULL</core>
<MemPortIdVec></MemPortIdVec>
<condition id="116">
<or_exp><and_exp><literal name="isNeg" val="0"/>
</and_exp></or_exp>
</condition>

<node id="23" bw="78" op_0_bw="32">
<![CDATA[
_ifconv:20  %tmp_18_i_i = zext i32 %sh_assign_1_cast to i78

]]></node>
<StgValue><ssdm name="tmp_18_i_i"/></StgValue>
</operation>

<operation id="46" st_id="2" stage="1" lat="1">
<core>Shift</core>
<MemPortIdVec></MemPortIdVec>
<condition id="111">
<or_exp><and_exp><literal name="isNeg" val="1"/>
</and_exp></or_exp>
</condition>

<node id="24" bw="24" op_0_bw="24" op_1_bw="24">
<![CDATA[
_ifconv:21  %tmp_19_i_i = lshr i24 %p_Result_1, %sh_assign_1_cast_cast

]]></node>
<StgValue><ssdm name="tmp_19_i_i"/></StgValue>
</operation>

<operation id="47" st_id="2" stage="1" lat="1">
<core>Shift</core>
<MemPortIdVec></MemPortIdVec>
<condition id="114">
<or_exp><and_exp><literal name="isNeg" val="0"/>
</and_exp></or_exp>
</condition>

<node id="25" bw="78" op_0_bw="78" op_1_bw="78">
<![CDATA[
_ifconv:22  %tmp_21_i_i = shl i78 %tmp_i_i, %tmp_18_i_i

]]></node>
<StgValue><ssdm name="tmp_21_i_i"/></StgValue>
</operation>

<operation id="48" st_id="2" stage="1" lat="1">
<core>NULL</core>
<MemPortIdVec></MemPortIdVec>
<condition id="110">
<or_exp><and_exp><literal name="isNeg" val="1"/>
</and_exp></or_exp>
</condition>

<node id="26" bw="1" op_0_bw="1" op_1_bw="24" op_2_bw="32">
<![CDATA[
_ifconv:23  %tmp = call i1 @_ssdm_op_BitSelect.i1.i24.i32(i24 %tmp_19_i_i, i32 23)

]]></node>
<StgValue><ssdm name="tmp"/></StgValue>
</operation>

<operation id="49" st_id="2" stage="1" lat="1">
<core>NULL</core>
<MemPortIdVec></MemPortIdVec>
<condition id="109">
<or_exp><and_exp><literal name="isNeg" val="1"/>
</and_exp></or_exp>
</condition>

<node id="27" bw="32" op_0_bw="1">
<![CDATA[
_ifconv:24  %tmp_s = zext i1 %tmp to i32

]]></node>
<StgValue><ssdm name="tmp_s"/></StgValue>
</operation>

<operation id="50" st_id="2" stage="1" lat="1">
<core>NULL</core>
<MemPortIdVec></MemPortIdVec>
<condition id="113">
<or_exp><and_exp><literal name="isNeg" val="0"/>
</and_exp></or_exp>
</condition>

<node id="28" bw="32" op_0_bw="32" op_1_bw="78" op_2_bw="32" op_3_bw="32">
<![CDATA[
_ifconv:25  %tmp_7 = call i32 @_ssdm_op_PartSelect.i32.i78.i32.i32(i78 %tmp_21_i_i, i32 23, i32 54)

]]></node>
<StgValue><ssdm name="tmp_7"/></StgValue>
</operation>

<operation id="51" st_id="2" stage="1" lat="1">
<core>Sel</core>
<MemPortIdVec></MemPortIdVec>
<condition id="35">
<or_exp><and_exp></and_exp></or_exp>
</condition>

<node id="29" bw="32" op_0_bw="1" op_1_bw="32" op_2_bw="32">
<![CDATA[
_ifconv:26  %p_Val2_3 = select i1 %isNeg, i32 %tmp_s, i32 %tmp_7

]]></node>
<StgValue><ssdm name="p_Val2_3"/></StgValue>
</operation>

<operation id="52" st_id="2" stage="1" lat="1">
<core>AddSub</core>
<MemPortIdVec></MemPortIdVec>
<condition id="119">
<or_exp><and_exp><literal name="p_Result_s" val="1"/>
</and_exp></or_exp>
</condition>

<node id="30" bw="32" op_0_bw="32" op_1_bw="32">
<![CDATA[
_ifconv:27  %p_Val2_8_i_i = sub i32 0, %p_Val2_3

]]></node>
<StgValue><ssdm name="p_Val2_8_i_i"/></StgValue>
</operation>

<operation id="53" st_id="2" stage="1" lat="1">
<core>Sel</core>
<MemPortIdVec></MemPortIdVec>
<condition id="35">
<or_exp><and_exp></and_exp></or_exp>
</condition>

<node id="31" bw="32" op_0_bw="1" op_1_bw="32" op_2_bw="32">
<![CDATA[
_ifconv:28  %p_Val2_5 = select i1 %p_Result_s, i32 %p_Val2_8_i_i, i32 %p_Val2_3

]]></node>
<StgValue><ssdm name="p_Val2_5"/></StgValue>
</operation>

<operation id="54" st_id="2" stage="1" lat="1">
<core>NULL</core>
<MemPortIdVec></MemPortIdVec>
<condition id="35">
<or_exp><and_exp></and_exp></or_exp>
</condition>

<node id="32" bw="0" op_0_bw="32" op_1_bw="0" op_2_bw="32" op_3_bw="0" op_4_bw="32" op_5_bw="0" op_6_bw="32" op_7_bw="0" op_8_bw="32" op_9_bw="0" op_10_bw="32" op_11_bw="0">
<![CDATA[
_ifconv:29  switch i32 %p_Val2_5, label %._crit_edge [
    i32 1, label %0
    i32 2, label %1
    i32 3, label %.preheader.i
    i32 4, label %2
    i32 5, label %3
  ]

]]></node>
<StgValue><ssdm name=""/></StgValue>
</operation>

<operation id="55" st_id="2" stage="2" lat="2">
<core></core>
<MemPortIdVec></MemPortIdVec>
<condition id="36">
<or_exp><and_exp><literal name="p_Val2_5" val="5"/>
</and_exp></or_exp>
</condition>

<node id="34" bw="0" op_0_bw="0" op_1_bw="32" op_2_bw="32">
<![CDATA[
:0  call fastcc void @dut_backproj(float* %strm_in_V, float* %strm_out_V)

]]></node>
<StgValue><ssdm name=""/></StgValue>
</operation>

<operation id="56" st_id="2" stage="2" lat="2">
<core></core>
<MemPortIdVec></MemPortIdVec>
<condition id="38">
<or_exp><and_exp><literal name="p_Val2_5" val="4"/>
</and_exp></or_exp>
</condition>

<node id="37" bw="0" op_0_bw="0" op_1_bw="32" op_2_bw="32">
<![CDATA[
:0  call fastcc void @dut_matmul(float* %strm_in_V, float* %strm_out_V)

]]></node>
<StgValue><ssdm name=""/></StgValue>
</operation>

<operation id="57" st_id="2" stage="2" lat="2">
<core></core>
<MemPortIdVec></MemPortIdVec>
<condition id="40">
<or_exp><and_exp><literal name="p_Val2_5" val="2"/>
</and_exp></or_exp>
</condition>

<node id="67" bw="0" op_0_bw="0" op_1_bw="32" op_2_bw="32">
<![CDATA[
:0  call fastcc void @dut_update_off_diag_r(float* %strm_in_V, float* %strm_out_V)

]]></node>
<StgValue><ssdm name=""/></StgValue>
</operation>

<operation id="58" st_id="2" stage="2" lat="2">
<core></core>
<MemPortIdVec></MemPortIdVec>
<condition id="42">
<or_exp><and_exp><literal name="p_Val2_5" val="1"/>
</and_exp></or_exp>
</condition>

<node id="70" bw="0" op_0_bw="0" op_1_bw="32" op_2_bw="32">
<![CDATA[
:0  call fastcc void @dut_calc_svd(float* %strm_in_V, float* %strm_out_V)

]]></node>
<StgValue><ssdm name=""/></StgValue>
</operation>
</state>

<state id="3" st_id="3">

<operation id="59" st_id="3" stage="1" lat="2">
<core></core>
<MemPortIdVec></MemPortIdVec>
<condition id="43">
<or_exp><and_exp><literal name="p_Val2_5" val="5"/>
</and_exp></or_exp>
</condition>

<node id="34" bw="0" op_0_bw="0" op_1_bw="32" op_2_bw="32">
<![CDATA[
:0  call fastcc void @dut_backproj(float* %strm_in_V, float* %strm_out_V)

]]></node>
<StgValue><ssdm name=""/></StgValue>
</operation>

<operation id="60" st_id="3" stage="1" lat="1">
<core>NULL</core>
<MemPortIdVec></MemPortIdVec>
<condition id="43">
<or_exp><and_exp><literal name="p_Val2_5" val="5"/>
</and_exp></or_exp>
</condition>

<node id="35" bw="0" op_0_bw="0">
<![CDATA[
:1  br label %._crit_edge

]]></node>
<StgValue><ssdm name=""/></StgValue>
</operation>

<operation id="61" st_id="3" stage="1" lat="2">
<core></core>
<MemPortIdVec></MemPortIdVec>
<condition id="44">
<or_exp><and_exp><literal name="p_Val2_5" val="4"/>
</and_exp></or_exp>
</condition>

<node id="37" bw="0" op_0_bw="0" op_1_bw="32" op_2_bw="32">
<![CDATA[
:0  call fastcc void @dut_matmul(float* %strm_in_V, float* %strm_out_V)

]]></node>
<StgValue><ssdm name=""/></StgValue>
</operation>

<operation id="62" st_id="3" stage="1" lat="1">
<core>NULL</core>
<MemPortIdVec></MemPortIdVec>
<condition id="44">
<or_exp><and_exp><literal name="p_Val2_5" val="4"/>
</and_exp></or_exp>
</condition>

<node id="38" bw="0" op_0_bw="0">
<![CDATA[
:1  br label %"update_off_diag_c<784, 784, MY_CONFIG_SVD>.exit"

]]></node>
<StgValue><ssdm name=""/></StgValue>
</operation>

<operation id="63" st_id="3" stage="1" lat="1">
<core>NULL</core>
<MemPortIdVec></MemPortIdVec>
<condition id="45">
<or_exp><and_exp><literal name="p_Val2_5" val="5"/>
</and_exp><and_exp><literal name="p_Val2_5" val="!1"/>
<literal name="p_Val2_5" val="!2"/>
<literal name="p_Val2_5" val="!3"/>
<literal name="p_Val2_5" val="!4"/>
</and_exp></or_exp>
</condition>

<node id="73" bw="0" op_0_bw="0">
<![CDATA[
._crit_edge:0  br label %"update_off_diag_c<784, 784, MY_CONFIG_SVD>.exit"

]]></node>
<StgValue><ssdm name=""/></StgValue>
</operation>
</state>

<state id="4" st_id="4">

<operation id="64" st_id="4" stage="1" lat="1">
<core>NULL</core>
<MemPortIdVec></MemPortIdVec>
<condition id="-1">
<or_exp><and_exp></and_exp></or_exp>
</condition>

<node id="40" bw="19" op_0_bw="19" op_1_bw="0">
<![CDATA[
.preheader.i:0  %indvar_flatten = phi i19 [ %indvar_flatten_next, %.preheader ], [ 0, %_ifconv ]

]]></node>
<StgValue><ssdm name="indvar_flatten"/></StgValue>
</operation>

<operation id="65" st_id="4" stage="1" lat="1">
<core>Cmp</core>
<MemPortIdVec></MemPortIdVec>
<condition id="-1">
<or_exp><and_exp></and_exp></or_exp>
</condition>

<node id="41" bw="1" op_0_bw="19" op_1_bw="19">
<![CDATA[
.preheader.i:1  %exitcond_flatten = icmp eq i19 %indvar_flatten, -217744

]]></node>
<StgValue><ssdm name="exitcond_flatten"/></StgValue>
</operation>

<operation id="66" st_id="4" stage="1" lat="1">
<core>AddSub</core>
<MemPortIdVec></MemPortIdVec>
<condition id="-1">
<or_exp><and_exp></and_exp></or_exp>
</condition>

<node id="42" bw="19" op_0_bw="19" op_1_bw="19">
<![CDATA[
.preheader.i:2  %indvar_flatten_next = add i19 %indvar_flatten, 1

]]></node>
<StgValue><ssdm name="indvar_flatten_next"/></StgValue>
</operation>

<operation id="67" st_id="4" stage="1" lat="1">
<core>NULL</core>
<MemPortIdVec></MemPortIdVec>
<condition id="-1">
<or_exp><and_exp></and_exp></or_exp>
</condition>

<node id="43" bw="0" op_0_bw="1" op_1_bw="0" op_2_bw="0">
<![CDATA[
.preheader.i:3  br i1 %exitcond_flatten, label %"update_off_diag_c<784, 784, MY_CONFIG_SVD>.exit", label %.preheader

]]></node>
<StgValue><ssdm name=""/></StgValue>
</operation>
</state>

<state id="5" st_id="5">

<operation id="68" st_id="5" stage="1" lat="1">
<core>FIFO</core>
<MemPortIdVec></MemPortIdVec>
<condition id="0">
<or_exp><and_exp><literal name="exitcond_flatten" val="0"/>
</and_exp></or_exp>
</condition>

<node id="50" bw="32" op_0_bw="32" op_1_bw="32">
<![CDATA[
.preheader:5  %tmp_129 = call float @_ssdm_op_Read.ap_fifo.volatile.floatP(float* %strm_in_V)

]]></node>
<StgValue><ssdm name="tmp_129"/></StgValue>
</operation>
</state>

<state id="6" st_id="6">

<operation id="69" st_id="6" stage="1" lat="1">
<core>FIFO</core>
<MemPortIdVec></MemPortIdVec>
<condition id="0">
<or_exp><and_exp><literal name="exitcond_flatten" val="0"/>
</and_exp></or_exp>
</condition>

<node id="51" bw="32" op_0_bw="32" op_1_bw="32">
<![CDATA[
.preheader:6  %tmp_130 = call float @_ssdm_op_Read.ap_fifo.volatile.floatP(float* %strm_in_V)

]]></node>
<StgValue><ssdm name="tmp_130"/></StgValue>
</operation>
</state>

<state id="7" st_id="7">

<operation id="70" st_id="7" stage="1" lat="1">
<core>FIFO</core>
<MemPortIdVec></MemPortIdVec>
<condition id="0">
<or_exp><and_exp><literal name="exitcond_flatten" val="0"/>
</and_exp></or_exp>
</condition>

<node id="52" bw="32" op_0_bw="32" op_1_bw="32">
<![CDATA[
.preheader:7  %tmp_131 = call float @_ssdm_op_Read.ap_fifo.volatile.floatP(float* %strm_in_V)

]]></node>
<StgValue><ssdm name="tmp_131"/></StgValue>
</operation>
</state>

<state id="8" st_id="8">

<operation id="71" st_id="8" stage="1" lat="1">
<core>FIFO</core>
<MemPortIdVec></MemPortIdVec>
<condition id="0">
<or_exp><and_exp><literal name="exitcond_flatten" val="0"/>
</and_exp></or_exp>
</condition>

<node id="53" bw="32" op_0_bw="32" op_1_bw="32">
<![CDATA[
.preheader:8  %tmp_132 = call float @_ssdm_op_Read.ap_fifo.volatile.floatP(float* %strm_in_V)

]]></node>
<StgValue><ssdm name="tmp_132"/></StgValue>
</operation>
</state>

<state id="9" st_id="9">

<operation id="72" st_id="9" stage="1" lat="1">
<core>FIFO</core>
<MemPortIdVec></MemPortIdVec>
<condition id="0">
<or_exp><and_exp><literal name="exitcond_flatten" val="0"/>
</and_exp></or_exp>
</condition>

<node id="54" bw="32" op_0_bw="32" op_1_bw="32">
<![CDATA[
.preheader:9  %tmp_133 = call float @_ssdm_op_Read.ap_fifo.volatile.floatP(float* %strm_in_V)

]]></node>
<StgValue><ssdm name="tmp_133"/></StgValue>
</operation>
</state>

<state id="10" st_id="10">

<operation id="73" st_id="10" stage="1" lat="1">
<core>FIFO</core>
<MemPortIdVec></MemPortIdVec>
<condition id="0">
<or_exp><and_exp><literal name="exitcond_flatten" val="0"/>
</and_exp></or_exp>
</condition>

<node id="55" bw="32" op_0_bw="32" op_1_bw="32">
<![CDATA[
.preheader:10  %tmp_134 = call float @_ssdm_op_Read.ap_fifo.volatile.floatP(float* %strm_in_V)

]]></node>
<StgValue><ssdm name="tmp_134"/></StgValue>
</operation>

<operation id="74" st_id="10" stage="4" lat="4">
<core>FMul</core>
<MemPortIdVec></MemPortIdVec>
<condition id="0">
<or_exp><and_exp><literal name="exitcond_flatten" val="0"/>
</and_exp></or_exp>
</condition>

<node id="56" bw="32" op_0_bw="32" op_1_bw="32">
<![CDATA[
.preheader:11  %tmp_i_i_20 = fmul float %tmp_129, %tmp_133

]]></node>
<StgValue><ssdm name="tmp_i_i_20"/></StgValue>
</operation>
</state>

<state id="11" st_id="11">

<operation id="75" st_id="11" stage="3" lat="4">
<core>FMul</core>
<MemPortIdVec></MemPortIdVec>
<condition id="0">
<or_exp><and_exp><literal name="exitcond_flatten" val="0"/>
</and_exp></or_exp>
</condition>

<node id="56" bw="32" op_0_bw="32" op_1_bw="32">
<![CDATA[
.preheader:11  %tmp_i_i_20 = fmul float %tmp_129, %tmp_133

]]></node>
<StgValue><ssdm name="tmp_i_i_20"/></StgValue>
</operation>

<operation id="76" st_id="11" stage="4" lat="4">
<core>FMul</core>
<MemPortIdVec></MemPortIdVec>
<condition id="0">
<or_exp><and_exp><literal name="exitcond_flatten" val="0"/>
</and_exp></or_exp>
</condition>

<node id="57" bw="32" op_0_bw="32" op_1_bw="32">
<![CDATA[
.preheader:12  %tmp_3_i_i = fmul float %tmp_131, %tmp_134

]]></node>
<StgValue><ssdm name="tmp_3_i_i"/></StgValue>
</operation>
</state>

<state id="12" st_id="12">

<operation id="77" st_id="12" stage="2" lat="4">
<core>FMul</core>
<MemPortIdVec></MemPortIdVec>
<condition id="0">
<or_exp><and_exp><literal name="exitcond_flatten" val="0"/>
</and_exp></or_exp>
</condition>

<node id="56" bw="32" op_0_bw="32" op_1_bw="32">
<![CDATA[
.preheader:11  %tmp_i_i_20 = fmul float %tmp_129, %tmp_133

]]></node>
<StgValue><ssdm name="tmp_i_i_20"/></StgValue>
</operation>

<operation id="78" st_id="12" stage="3" lat="4">
<core>FMul</core>
<MemPortIdVec></MemPortIdVec>
<condition id="0">
<or_exp><and_exp><literal name="exitcond_flatten" val="0"/>
</and_exp></or_exp>
</condition>

<node id="57" bw="32" op_0_bw="32" op_1_bw="32">
<![CDATA[
.preheader:12  %tmp_3_i_i = fmul float %tmp_131, %tmp_134

]]></node>
<StgValue><ssdm name="tmp_3_i_i"/></StgValue>
</operation>

<operation id="79" st_id="12" stage="4" lat="4">
<core>FMul</core>
<MemPortIdVec></MemPortIdVec>
<condition id="0">
<or_exp><and_exp><literal name="exitcond_flatten" val="0"/>
</and_exp></or_exp>
</condition>

<node id="59" bw="32" op_0_bw="32" op_1_bw="32">
<![CDATA[
.preheader:14  %tmp_i10_i = fmul float %tmp_130, %tmp_133

]]></node>
<StgValue><ssdm name="tmp_i10_i"/></StgValue>
</operation>
</state>

<state id="13" st_id="13">

<operation id="80" st_id="13" stage="1" lat="4">
<core>FMul</core>
<MemPortIdVec></MemPortIdVec>
<condition id="0">
<or_exp><and_exp><literal name="exitcond_flatten" val="0"/>
</and_exp></or_exp>
</condition>

<node id="56" bw="32" op_0_bw="32" op_1_bw="32">
<![CDATA[
.preheader:11  %tmp_i_i_20 = fmul float %tmp_129, %tmp_133

]]></node>
<StgValue><ssdm name="tmp_i_i_20"/></StgValue>
</operation>

<operation id="81" st_id="13" stage="2" lat="4">
<core>FMul</core>
<MemPortIdVec></MemPortIdVec>
<condition id="0">
<or_exp><and_exp><literal name="exitcond_flatten" val="0"/>
</and_exp></or_exp>
</condition>

<node id="57" bw="32" op_0_bw="32" op_1_bw="32">
<![CDATA[
.preheader:12  %tmp_3_i_i = fmul float %tmp_131, %tmp_134

]]></node>
<StgValue><ssdm name="tmp_3_i_i"/></StgValue>
</operation>

<operation id="82" st_id="13" stage="3" lat="4">
<core>FMul</core>
<MemPortIdVec></MemPortIdVec>
<condition id="0">
<or_exp><and_exp><literal name="exitcond_flatten" val="0"/>
</and_exp></or_exp>
</condition>

<node id="59" bw="32" op_0_bw="32" op_1_bw="32">
<![CDATA[
.preheader:14  %tmp_i10_i = fmul float %tmp_130, %tmp_133

]]></node>
<StgValue><ssdm name="tmp_i10_i"/></StgValue>
</operation>

<operation id="83" st_id="13" stage="4" lat="4">
<core>FMul</core>
<MemPortIdVec></MemPortIdVec>
<condition id="0">
<or_exp><and_exp><literal name="exitcond_flatten" val="0"/>
</and_exp></or_exp>
</condition>

<node id="60" bw="32" op_0_bw="32" op_1_bw="32">
<![CDATA[
.preheader:15  %tmp_3_i11_i = fmul float %tmp_132, %tmp_134

]]></node>
<StgValue><ssdm name="tmp_3_i11_i"/></StgValue>
</operation>
</state>

<state id="14" st_id="14">

<operation id="84" st_id="14" stage="1" lat="4">
<core>FMul</core>
<MemPortIdVec></MemPortIdVec>
<condition id="0">
<or_exp><and_exp><literal name="exitcond_flatten" val="0"/>
</and_exp></or_exp>
</condition>

<node id="57" bw="32" op_0_bw="32" op_1_bw="32">
<![CDATA[
.preheader:12  %tmp_3_i_i = fmul float %tmp_131, %tmp_134

]]></node>
<StgValue><ssdm name="tmp_3_i_i"/></StgValue>
</operation>

<operation id="85" st_id="14" stage="2" lat="4">
<core>FMul</core>
<MemPortIdVec></MemPortIdVec>
<condition id="0">
<or_exp><and_exp><literal name="exitcond_flatten" val="0"/>
</and_exp></or_exp>
</condition>

<node id="59" bw="32" op_0_bw="32" op_1_bw="32">
<![CDATA[
.preheader:14  %tmp_i10_i = fmul float %tmp_130, %tmp_133

]]></node>
<StgValue><ssdm name="tmp_i10_i"/></StgValue>
</operation>

<operation id="86" st_id="14" stage="3" lat="4">
<core>FMul</core>
<MemPortIdVec></MemPortIdVec>
<condition id="0">
<or_exp><and_exp><literal name="exitcond_flatten" val="0"/>
</and_exp></or_exp>
</condition>

<node id="60" bw="32" op_0_bw="32" op_1_bw="32">
<![CDATA[
.preheader:15  %tmp_3_i11_i = fmul float %tmp_132, %tmp_134

]]></node>
<StgValue><ssdm name="tmp_3_i11_i"/></StgValue>
</operation>
</state>

<state id="15" st_id="15">

<operation id="87" st_id="15" stage="5" lat="5">
<core>FAddSub</core>
<MemPortIdVec></MemPortIdVec>
<condition id="0">
<or_exp><and_exp><literal name="exitcond_flatten" val="0"/>
</and_exp></or_exp>
</condition>

<node id="58" bw="32" op_0_bw="32" op_1_bw="32">
<![CDATA[
.preheader:13  %tmp_126 = fadd float %tmp_i_i_20, %tmp_3_i_i

]]></node>
<StgValue><ssdm name="tmp_126"/></StgValue>
</operation>

<operation id="88" st_id="15" stage="1" lat="4">
<core>FMul</core>
<MemPortIdVec></MemPortIdVec>
<condition id="0">
<or_exp><and_exp><literal name="exitcond_flatten" val="0"/>
</and_exp></or_exp>
</condition>

<node id="59" bw="32" op_0_bw="32" op_1_bw="32">
<![CDATA[
.preheader:14  %tmp_i10_i = fmul float %tmp_130, %tmp_133

]]></node>
<StgValue><ssdm name="tmp_i10_i"/></StgValue>
</operation>

<operation id="89" st_id="15" stage="2" lat="4">
<core>FMul</core>
<MemPortIdVec></MemPortIdVec>
<condition id="0">
<or_exp><and_exp><literal name="exitcond_flatten" val="0"/>
</and_exp></or_exp>
</condition>

<node id="60" bw="32" op_0_bw="32" op_1_bw="32">
<![CDATA[
.preheader:15  %tmp_3_i11_i = fmul float %tmp_132, %tmp_134

]]></node>
<StgValue><ssdm name="tmp_3_i11_i"/></StgValue>
</operation>
</state>

<state id="16" st_id="16">

<operation id="90" st_id="16" stage="4" lat="5">
<core>FAddSub</core>
<MemPortIdVec></MemPortIdVec>
<condition id="0">
<or_exp><and_exp><literal name="exitcond_flatten" val="0"/>
</and_exp></or_exp>
</condition>

<node id="58" bw="32" op_0_bw="32" op_1_bw="32">
<![CDATA[
.preheader:13  %tmp_126 = fadd float %tmp_i_i_20, %tmp_3_i_i

]]></node>
<StgValue><ssdm name="tmp_126"/></StgValue>
</operation>

<operation id="91" st_id="16" stage="1" lat="4">
<core>FMul</core>
<MemPortIdVec></MemPortIdVec>
<condition id="0">
<or_exp><and_exp><literal name="exitcond_flatten" val="0"/>
</and_exp></or_exp>
</condition>

<node id="60" bw="32" op_0_bw="32" op_1_bw="32">
<![CDATA[
.preheader:15  %tmp_3_i11_i = fmul float %tmp_132, %tmp_134

]]></node>
<StgValue><ssdm name="tmp_3_i11_i"/></StgValue>
</operation>
</state>

<state id="17" st_id="17">

<operation id="92" st_id="17" stage="3" lat="5">
<core>FAddSub</core>
<MemPortIdVec></MemPortIdVec>
<condition id="0">
<or_exp><and_exp><literal name="exitcond_flatten" val="0"/>
</and_exp></or_exp>
</condition>

<node id="58" bw="32" op_0_bw="32" op_1_bw="32">
<![CDATA[
.preheader:13  %tmp_126 = fadd float %tmp_i_i_20, %tmp_3_i_i

]]></node>
<StgValue><ssdm name="tmp_126"/></StgValue>
</operation>

<operation id="93" st_id="17" stage="5" lat="5">
<core>FAddSub</core>
<MemPortIdVec></MemPortIdVec>
<condition id="0">
<or_exp><and_exp><literal name="exitcond_flatten" val="0"/>
</and_exp></or_exp>
</condition>

<node id="61" bw="32" op_0_bw="32" op_1_bw="32">
<![CDATA[
.preheader:16  %tmp_127 = fadd float %tmp_i10_i, %tmp_3_i11_i

]]></node>
<StgValue><ssdm name="tmp_127"/></StgValue>
</operation>
</state>

<state id="18" st_id="18">

<operation id="94" st_id="18" stage="2" lat="5">
<core>FAddSub</core>
<MemPortIdVec></MemPortIdVec>
<condition id="0">
<or_exp><and_exp><literal name="exitcond_flatten" val="0"/>
</and_exp></or_exp>
</condition>

<node id="58" bw="32" op_0_bw="32" op_1_bw="32">
<![CDATA[
.preheader:13  %tmp_126 = fadd float %tmp_i_i_20, %tmp_3_i_i

]]></node>
<StgValue><ssdm name="tmp_126"/></StgValue>
</operation>

<operation id="95" st_id="18" stage="4" lat="5">
<core>FAddSub</core>
<MemPortIdVec></MemPortIdVec>
<condition id="0">
<or_exp><and_exp><literal name="exitcond_flatten" val="0"/>
</and_exp></or_exp>
</condition>

<node id="61" bw="32" op_0_bw="32" op_1_bw="32">
<![CDATA[
.preheader:16  %tmp_127 = fadd float %tmp_i10_i, %tmp_3_i11_i

]]></node>
<StgValue><ssdm name="tmp_127"/></StgValue>
</operation>
</state>

<state id="19" st_id="19">

<operation id="96" st_id="19" stage="1" lat="5">
<core>FAddSub</core>
<MemPortIdVec></MemPortIdVec>
<condition id="0">
<or_exp><and_exp><literal name="exitcond_flatten" val="0"/>
</and_exp></or_exp>
</condition>

<node id="58" bw="32" op_0_bw="32" op_1_bw="32">
<![CDATA[
.preheader:13  %tmp_126 = fadd float %tmp_i_i_20, %tmp_3_i_i

]]></node>
<StgValue><ssdm name="tmp_126"/></StgValue>
</operation>

<operation id="97" st_id="19" stage="3" lat="5">
<core>FAddSub</core>
<MemPortIdVec></MemPortIdVec>
<condition id="0">
<or_exp><and_exp><literal name="exitcond_flatten" val="0"/>
</and_exp></or_exp>
</condition>

<node id="61" bw="32" op_0_bw="32" op_1_bw="32">
<![CDATA[
.preheader:16  %tmp_127 = fadd float %tmp_i10_i, %tmp_3_i11_i

]]></node>
<StgValue><ssdm name="tmp_127"/></StgValue>
</operation>
</state>

<state id="20" st_id="20">

<operation id="98" st_id="20" stage="2" lat="5">
<core>FAddSub</core>
<MemPortIdVec></MemPortIdVec>
<condition id="0">
<or_exp><and_exp><literal name="exitcond_flatten" val="0"/>
</and_exp></or_exp>
</condition>

<node id="61" bw="32" op_0_bw="32" op_1_bw="32">
<![CDATA[
.preheader:16  %tmp_127 = fadd float %tmp_i10_i, %tmp_3_i11_i

]]></node>
<StgValue><ssdm name="tmp_127"/></StgValue>
</operation>

<operation id="99" st_id="20" stage="1" lat="1">
<core>FIFO</core>
<MemPortIdVec></MemPortIdVec>
<condition id="0">
<or_exp><and_exp><literal name="exitcond_flatten" val="0"/>
</and_exp></or_exp>
</condition>

<node id="62" bw="0" op_0_bw="0" op_1_bw="32" op_2_bw="32">
<![CDATA[
.preheader:17  call void @_ssdm_op_Write.ap_fifo.volatile.floatP(float* %strm_out_V, float %tmp_126)

]]></node>
<StgValue><ssdm name=""/></StgValue>
</operation>
</state>

<state id="21" st_id="21">

<operation id="100" st_id="21" stage="1" lat="5">
<core>FAddSub</core>
<MemPortIdVec></MemPortIdVec>
<condition id="0">
<or_exp><and_exp><literal name="exitcond_flatten" val="0"/>
</and_exp></or_exp>
</condition>

<node id="61" bw="32" op_0_bw="32" op_1_bw="32">
<![CDATA[
.preheader:16  %tmp_127 = fadd float %tmp_i10_i, %tmp_3_i11_i

]]></node>
<StgValue><ssdm name="tmp_127"/></StgValue>
</operation>
</state>

<state id="22" st_id="22">

<operation id="101" st_id="22" stage="1" lat="1">
<core>NULL</core>
<MemPortIdVec></MemPortIdVec>
<condition id="0">
<or_exp><and_exp><literal name="exitcond_flatten" val="0"/>
</and_exp></or_exp>
</condition>

<node id="45" bw="0" op_0_bw="0" op_1_bw="0">
<![CDATA[
.preheader:0  call void (...)* @_ssdm_op_SpecLoopName([17 x i8]* @L_svd_calc_off_c_str)

]]></node>
<StgValue><ssdm name=""/></StgValue>
</operation>

<operation id="102" st_id="22" stage="1" lat="1">
<core>NULL</core>
<MemPortIdVec></MemPortIdVec>
<condition id="0">
<or_exp><and_exp><literal name="exitcond_flatten" val="0"/>
</and_exp></or_exp>
</condition>

<node id="46" bw="32" op_0_bw="32" op_1_bw="64" op_2_bw="64" op_3_bw="64">
<![CDATA[
.preheader:1  %empty_19 = call i32 (...)* @_ssdm_op_SpecLoopTripCount(i64 306544, i64 306544, i64 306544)

]]></node>
<StgValue><ssdm name="empty_19"/></StgValue>
</operation>

<operation id="103" st_id="22" stage="1" lat="1">
<core>NULL</core>
<MemPortIdVec></MemPortIdVec>
<condition id="0">
<or_exp><and_exp><literal name="exitcond_flatten" val="0"/>
</and_exp></or_exp>
</condition>

<node id="47" bw="0" op_0_bw="0" op_1_bw="0">
<![CDATA[
.preheader:2  call void (...)* @_ssdm_op_SpecLoopName([15 x i8]* @p_str1810) nounwind

]]></node>
<StgValue><ssdm name=""/></StgValue>
</operation>

<operation id="104" st_id="22" stage="1" lat="1">
<core>NULL</core>
<MemPortIdVec></MemPortIdVec>
<condition id="0">
<or_exp><and_exp><literal name="exitcond_flatten" val="0"/>
</and_exp></or_exp>
</condition>

<node id="48" bw="32" op_0_bw="32" op_1_bw="0">
<![CDATA[
.preheader:3  %tmp_32_i = call i32 (...)* @_ssdm_op_SpecRegionBegin([15 x i8]* @p_str1810)

]]></node>
<StgValue><ssdm name="tmp_32_i"/></StgValue>
</operation>

<operation id="105" st_id="22" stage="1" lat="1">
<core>NULL</core>
<MemPortIdVec></MemPortIdVec>
<condition id="0">
<or_exp><and_exp><literal name="exitcond_flatten" val="0"/>
</and_exp></or_exp>
</condition>

<node id="49" bw="0" op_0_bw="0" op_1_bw="32" op_2_bw="32" op_3_bw="32" op_4_bw="32" op_5_bw="0">
<![CDATA[
.preheader:4  call void (...)* @_ssdm_op_SpecPipeline(i32 -1, i32 1, i32 1, i32 0, [1 x i8]* @p_str1806) nounwind

]]></node>
<StgValue><ssdm name=""/></StgValue>
</operation>

<operation id="106" st_id="22" stage="1" lat="1">
<core>FIFO</core>
<MemPortIdVec></MemPortIdVec>
<condition id="0">
<or_exp><and_exp><literal name="exitcond_flatten" val="0"/>
</and_exp></or_exp>
</condition>

<node id="63" bw="0" op_0_bw="0" op_1_bw="32" op_2_bw="32">
<![CDATA[
.preheader:18  call void @_ssdm_op_Write.ap_fifo.volatile.floatP(float* %strm_out_V, float %tmp_127)

]]></node>
<StgValue><ssdm name=""/></StgValue>
</operation>

<operation id="107" st_id="22" stage="1" lat="1">
<core>NULL</core>
<MemPortIdVec></MemPortIdVec>
<condition id="0">
<or_exp><and_exp><literal name="exitcond_flatten" val="0"/>
</and_exp></or_exp>
</condition>

<node id="64" bw="32" op_0_bw="32" op_1_bw="0" op_2_bw="32">
<![CDATA[
.preheader:19  %empty_21 = call i32 (...)* @_ssdm_op_SpecRegionEnd([15 x i8]* @p_str1810, i32 %tmp_32_i)

]]></node>
<StgValue><ssdm name="empty_21"/></StgValue>
</operation>

<operation id="108" st_id="22" stage="1" lat="1">
<core>NULL</core>
<MemPortIdVec></MemPortIdVec>
<condition id="0">
<or_exp><and_exp><literal name="exitcond_flatten" val="0"/>
</and_exp></or_exp>
</condition>

<node id="65" bw="0" op_0_bw="0">
<![CDATA[
.preheader:20  br label %.preheader.i

]]></node>
<StgValue><ssdm name=""/></StgValue>
</operation>
</state>

<state id="23" st_id="23">

<operation id="109" st_id="23" stage="1" lat="2">
<core></core>
<MemPortIdVec></MemPortIdVec>
<condition id="46">
<or_exp><and_exp><literal name="p_Val2_5" val="2"/>
</and_exp></or_exp>
</condition>

<node id="67" bw="0" op_0_bw="0" op_1_bw="32" op_2_bw="32">
<![CDATA[
:0  call fastcc void @dut_update_off_diag_r(float* %strm_in_V, float* %strm_out_V)

]]></node>
<StgValue><ssdm name=""/></StgValue>
</operation>

<operation id="110" st_id="23" stage="1" lat="1">
<core>NULL</core>
<MemPortIdVec></MemPortIdVec>
<condition id="46">
<or_exp><and_exp><literal name="p_Val2_5" val="2"/>
</and_exp></or_exp>
</condition>

<node id="68" bw="0" op_0_bw="0">
<![CDATA[
:1  br label %"update_off_diag_c<784, 784, MY_CONFIG_SVD>.exit"

]]></node>
<StgValue><ssdm name=""/></StgValue>
</operation>

<operation id="111" st_id="23" stage="1" lat="2">
<core></core>
<MemPortIdVec></MemPortIdVec>
<condition id="47">
<or_exp><and_exp><literal name="p_Val2_5" val="1"/>
</and_exp></or_exp>
</condition>

<node id="70" bw="0" op_0_bw="0" op_1_bw="32" op_2_bw="32">
<![CDATA[
:0  call fastcc void @dut_calc_svd(float* %strm_in_V, float* %strm_out_V)

]]></node>
<StgValue><ssdm name=""/></StgValue>
</operation>

<operation id="112" st_id="23" stage="1" lat="1">
<core>NULL</core>
<MemPortIdVec></MemPortIdVec>
<condition id="47">
<or_exp><and_exp><literal name="p_Val2_5" val="1"/>
</and_exp></or_exp>
</condition>

<node id="71" bw="0" op_0_bw="0">
<![CDATA[
:1  br label %"update_off_diag_c<784, 784, MY_CONFIG_SVD>.exit"

]]></node>
<StgValue><ssdm name=""/></StgValue>
</operation>
</state>

<state id="24" st_id="24">

<operation id="113" st_id="24" stage="1" lat="1">
<core>NULL</core>
<MemPortIdVec></MemPortIdVec>
<condition id="48">
<or_exp><and_exp></and_exp></or_exp>
</condition>

<node id="75" bw="0">
<![CDATA[
update_off_diag_c<784, 784, MY_CONFIG_SVD>.exit:0  ret void

]]></node>
<StgValue><ssdm name=""/></StgValue>
</operation>
</state>
</state_list>


<ports>
<port id="167" name="strm_in_V" dir="0" iftype="3">
<core>FIFO</core><StgValue><ssdm name="strm_in_V"/></StgValue>
</port>
<port id="168" name="strm_out_V" dir="1" iftype="3">
<core>FIFO</core><StgValue><ssdm name="strm_out_V"/></StgValue>
</port>
</ports>


<dataflows>
<dataflow id="170" from="_ssdm_op_Read.ap_fifo.volatile.floatP" to="tmp_128" fromId="169" toId="25">
</dataflow>
<dataflow id="171" from="strm_in_V" to="tmp_128" fromId="167" toId="25">
</dataflow>
<dataflow id="172" from="tmp_128" to="p_Val2_s" fromId="25" toId="26">
</dataflow>
<dataflow id="174" from="_ssdm_op_BitSelect.i1.i32.i32" to="p_Result_s" fromId="173" toId="27">
</dataflow>
<dataflow id="175" from="p_Val2_s" to="p_Result_s" fromId="26" toId="27">
</dataflow>
<dataflow id="177" from="stg_176" to="p_Result_s" fromId="176" toId="27">
</dataflow>
<dataflow id="179" from="_ssdm_op_PartSelect.i8.i32.i32.i32" to="loc_V" fromId="178" toId="28">
</dataflow>
<dataflow id="180" from="p_Val2_s" to="loc_V" fromId="26" toId="28">
</dataflow>
<dataflow id="182" from="stg_181" to="loc_V" fromId="181" toId="28">
</dataflow>
<dataflow id="184" from="stg_183" to="loc_V" fromId="183" toId="28">
</dataflow>
<dataflow id="185" from="p_Val2_s" to="loc_V_1" fromId="26" toId="29">
</dataflow>
<dataflow id="186" from="loc_V" to="tmp_i_i_i_cast1" fromId="28" toId="30">
</dataflow>
<dataflow id="188" from="stg_187" to="sh_assign" fromId="187" toId="31">
</dataflow>
<dataflow id="189" from="tmp_i_i_i_cast1" to="sh_assign" fromId="30" toId="31">
</dataflow>
<dataflow id="191" from="_ssdm_op_BitSelect.i1.i9.i32" to="isNeg" fromId="190" toId="32">
</dataflow>
<dataflow id="192" from="sh_assign" to="isNeg" fromId="31" toId="32">
</dataflow>
<dataflow id="194" from="stg_193" to="isNeg" fromId="193" toId="32">
</dataflow>
<dataflow id="196" from="stg_195" to="tmp_17_i_i" fromId="195" toId="33">
</dataflow>
<dataflow id="197" from="loc_V" to="tmp_17_i_i" fromId="28" toId="33">
</dataflow>
<dataflow id="198" from="tmp_17_i_i" to="tmp_17_i_i_cast" fromId="33" toId="34">
</dataflow>
<dataflow id="199" from="isNeg" to="sh_assign_1" fromId="32" toId="35">
</dataflow>
<dataflow id="200" from="tmp_17_i_i_cast" to="sh_assign_1" fromId="34" toId="35">
</dataflow>
<dataflow id="201" from="sh_assign" to="sh_assign_1" fromId="31" toId="35">
</dataflow>
<dataflow id="203" from="_ssdm_op_SpecInterface" to="empty" fromId="202" toId="36">
</dataflow>
<dataflow id="204" from="strm_out_V" to="empty" fromId="168" toId="36">
</dataflow>
<dataflow id="206" from="ap_fifo_str" to="empty" fromId="205" toId="36">
</dataflow>
<dataflow id="208" from="stg_207" to="empty" fromId="207" toId="36">
</dataflow>
<dataflow id="209" from="stg_207" to="empty" fromId="207" toId="36">
</dataflow>
<dataflow id="210" from="stg_207" to="empty" fromId="207" toId="36">
</dataflow>
<dataflow id="211" from="stg_207" to="empty" fromId="207" toId="36">
</dataflow>
<dataflow id="213" from="p_str" to="empty" fromId="212" toId="36">
</dataflow>
<dataflow id="214" from="p_str" to="empty" fromId="212" toId="36">
</dataflow>
<dataflow id="215" from="p_str" to="empty" fromId="212" toId="36">
</dataflow>
<dataflow id="217" from="stg_216" to="empty" fromId="216" toId="36">
</dataflow>
<dataflow id="218" from="stg_216" to="empty" fromId="216" toId="36">
</dataflow>
<dataflow id="220" from="stg_219" to="empty" fromId="219" toId="36">
</dataflow>
<dataflow id="221" from="stg_219" to="empty" fromId="219" toId="36">
</dataflow>
<dataflow id="222" from="p_str" to="empty" fromId="212" toId="36">
</dataflow>
<dataflow id="223" from="_ssdm_op_SpecInterface" to="empty_18" fromId="202" toId="37">
</dataflow>
<dataflow id="224" from="strm_in_V" to="empty_18" fromId="167" toId="37">
</dataflow>
<dataflow id="225" from="ap_fifo_str" to="empty_18" fromId="205" toId="37">
</dataflow>
<dataflow id="226" from="stg_207" to="empty_18" fromId="207" toId="37">
</dataflow>
<dataflow id="227" from="stg_207" to="empty_18" fromId="207" toId="37">
</dataflow>
<dataflow id="228" from="stg_207" to="empty_18" fromId="207" toId="37">
</dataflow>
<dataflow id="229" from="stg_207" to="empty_18" fromId="207" toId="37">
</dataflow>
<dataflow id="230" from="p_str" to="empty_18" fromId="212" toId="37">
</dataflow>
<dataflow id="231" from="p_str" to="empty_18" fromId="212" toId="37">
</dataflow>
<dataflow id="232" from="p_str" to="empty_18" fromId="212" toId="37">
</dataflow>
<dataflow id="233" from="stg_216" to="empty_18" fromId="216" toId="37">
</dataflow>
<dataflow id="234" from="stg_216" to="empty_18" fromId="216" toId="37">
</dataflow>
<dataflow id="235" from="stg_219" to="empty_18" fromId="219" toId="37">
</dataflow>
<dataflow id="236" from="stg_219" to="empty_18" fromId="219" toId="37">
</dataflow>
<dataflow id="237" from="p_str" to="empty_18" fromId="212" toId="37">
</dataflow>
<dataflow id="239" from="_ssdm_op_SpecBitsMap" to="stg_38" fromId="238" toId="38">
</dataflow>
<dataflow id="240" from="strm_in_V" to="stg_38" fromId="167" toId="38">
</dataflow>
<dataflow id="241" from="_ssdm_op_SpecBitsMap" to="stg_39" fromId="238" toId="39">
</dataflow>
<dataflow id="242" from="strm_out_V" to="stg_39" fromId="168" toId="39">
</dataflow>
<dataflow id="244" from="_ssdm_op_SpecTopModule" to="stg_40" fromId="243" toId="40">
</dataflow>
<dataflow id="246" from="dut_str" to="stg_40" fromId="245" toId="40">
</dataflow>
<dataflow id="248" from="_ssdm_op_BitConcatenate.i24.i1.i23" to="p_Result_1" fromId="247" toId="41">
</dataflow>
<dataflow id="250" from="stg_249" to="p_Result_1" fromId="249" toId="41">
</dataflow>
<dataflow id="251" from="loc_V_1" to="p_Result_1" fromId="29" toId="41">
</dataflow>
<dataflow id="252" from="p_Result_1" to="tmp_i_i" fromId="41" toId="42">
</dataflow>
<dataflow id="253" from="sh_assign_1" to="sh_assign_1_cast" fromId="35" toId="43">
</dataflow>
<dataflow id="254" from="sh_assign_1" to="sh_assign_1_cast_cast" fromId="35" toId="44">
</dataflow>
<dataflow id="255" from="sh_assign_1_cast" to="tmp_18_i_i" fromId="43" toId="45">
</dataflow>
<dataflow id="256" from="p_Result_1" to="tmp_19_i_i" fromId="41" toId="46">
</dataflow>
<dataflow id="257" from="sh_assign_1_cast_cast" to="tmp_19_i_i" fromId="44" toId="46">
</dataflow>
<dataflow id="258" from="tmp_i_i" to="tmp_21_i_i" fromId="42" toId="47">
</dataflow>
<dataflow id="259" from="tmp_18_i_i" to="tmp_21_i_i" fromId="45" toId="47">
</dataflow>
<dataflow id="261" from="_ssdm_op_BitSelect.i1.i24.i32" to="tmp" fromId="260" toId="48">
</dataflow>
<dataflow id="262" from="tmp_19_i_i" to="tmp" fromId="46" toId="48">
</dataflow>
<dataflow id="263" from="stg_181" to="tmp" fromId="181" toId="48">
</dataflow>
<dataflow id="264" from="tmp" to="tmp_s" fromId="48" toId="49">
</dataflow>
<dataflow id="266" from="_ssdm_op_PartSelect.i32.i78.i32.i32" to="tmp_7" fromId="265" toId="50">
</dataflow>
<dataflow id="267" from="tmp_21_i_i" to="tmp_7" fromId="47" toId="50">
</dataflow>
<dataflow id="268" from="stg_181" to="tmp_7" fromId="181" toId="50">
</dataflow>
<dataflow id="270" from="stg_269" to="tmp_7" fromId="269" toId="50">
</dataflow>
<dataflow id="271" from="isNeg" to="p_Val2_3" fromId="32" toId="51">
</dataflow>
<dataflow id="272" from="tmp_s" to="p_Val2_3" fromId="49" toId="51">
</dataflow>
<dataflow id="273" from="tmp_7" to="p_Val2_3" fromId="50" toId="51">
</dataflow>
<dataflow id="274" from="stg_207" to="p_Val2_8_i_i" fromId="207" toId="52">
</dataflow>
<dataflow id="275" from="p_Val2_3" to="p_Val2_8_i_i" fromId="51" toId="52">
</dataflow>
<dataflow id="276" from="p_Result_s" to="p_Val2_5" fromId="27" toId="53">
</dataflow>
<dataflow id="277" from="p_Val2_8_i_i" to="p_Val2_5" fromId="52" toId="53">
</dataflow>
<dataflow id="278" from="p_Val2_3" to="p_Val2_5" fromId="51" toId="53">
</dataflow>
<dataflow id="279" from="p_Val2_5" to="stg_54" fromId="53" toId="54">
</dataflow>
<dataflow id="281" from="stg_280" to="stg_54" fromId="280" toId="54">
</dataflow>
<dataflow id="282" from="stg_216" to="stg_54" fromId="216" toId="54">
</dataflow>
<dataflow id="284" from="stg_283" to="stg_54" fromId="283" toId="54">
</dataflow>
<dataflow id="286" from="stg_285" to="stg_54" fromId="285" toId="54">
</dataflow>
<dataflow id="288" from="stg_287" to="stg_54" fromId="287" toId="54">
</dataflow>
<dataflow id="290" from="dut_backproj" to="stg_55" fromId="289" toId="55">
</dataflow>
<dataflow id="291" from="strm_in_V" to="stg_55" fromId="167" toId="55">
</dataflow>
<dataflow id="292" from="strm_out_V" to="stg_55" fromId="168" toId="55">
</dataflow>
<dataflow id="294" from="dut_matmul" to="stg_56" fromId="293" toId="56">
</dataflow>
<dataflow id="295" from="strm_in_V" to="stg_56" fromId="167" toId="56">
</dataflow>
<dataflow id="296" from="strm_out_V" to="stg_56" fromId="168" toId="56">
</dataflow>
<dataflow id="298" from="dut_update_off_diag_r" to="stg_57" fromId="297" toId="57">
</dataflow>
<dataflow id="299" from="strm_in_V" to="stg_57" fromId="167" toId="57">
</dataflow>
<dataflow id="300" from="strm_out_V" to="stg_57" fromId="168" toId="57">
</dataflow>
<dataflow id="302" from="dut_calc_svd" to="stg_58" fromId="301" toId="58">
</dataflow>
<dataflow id="303" from="strm_in_V" to="stg_58" fromId="167" toId="58">
</dataflow>
<dataflow id="304" from="strm_out_V" to="stg_58" fromId="168" toId="58">
</dataflow>
<dataflow id="305" from="dut_backproj" to="stg_59" fromId="289" toId="59">
</dataflow>
<dataflow id="306" from="strm_in_V" to="stg_59" fromId="167" toId="59">
</dataflow>
<dataflow id="307" from="strm_out_V" to="stg_59" fromId="168" toId="59">
</dataflow>
<dataflow id="308" from="dut_matmul" to="stg_61" fromId="293" toId="61">
</dataflow>
<dataflow id="309" from="strm_in_V" to="stg_61" fromId="167" toId="61">
</dataflow>
<dataflow id="310" from="strm_out_V" to="stg_61" fromId="168" toId="61">
</dataflow>
<dataflow id="311" from="indvar_flatten_next" to="indvar_flatten" fromId="66" toId="64">
<BackEdge/>
<condition id="186">
<or_exp><and_exp><literal name="exitcond_flatten" val="0"/>
</and_exp></or_exp>
</condition>
</dataflow>
<dataflow id="312" from="stg_108" to="indvar_flatten" fromId="108" toId="64">
<BackEdge/>
</dataflow>
<dataflow id="314" from="stg_313" to="indvar_flatten" fromId="313" toId="64">
<condition id="187">
<or_exp><and_exp><literal name="p_Val2_5" val="3"/>
</and_exp></or_exp>
</condition>
</dataflow>
<dataflow id="315" from="stg_54" to="indvar_flatten" fromId="54" toId="64">
</dataflow>
<dataflow id="316" from="indvar_flatten" to="exitcond_flatten" fromId="64" toId="65">
</dataflow>
<dataflow id="318" from="stg_317" to="exitcond_flatten" fromId="317" toId="65">
</dataflow>
<dataflow id="319" from="indvar_flatten" to="indvar_flatten_next" fromId="64" toId="66">
</dataflow>
<dataflow id="321" from="stg_320" to="indvar_flatten_next" fromId="320" toId="66">
</dataflow>
<dataflow id="322" from="exitcond_flatten" to="stg_67" fromId="65" toId="67">
</dataflow>
<dataflow id="323" from="_ssdm_op_Read.ap_fifo.volatile.floatP" to="tmp_129" fromId="169" toId="68">
</dataflow>
<dataflow id="324" from="strm_in_V" to="tmp_129" fromId="167" toId="68">
</dataflow>
<dataflow id="325" from="_ssdm_op_Read.ap_fifo.volatile.floatP" to="tmp_130" fromId="169" toId="69">
</dataflow>
<dataflow id="326" from="strm_in_V" to="tmp_130" fromId="167" toId="69">
</dataflow>
<dataflow id="327" from="_ssdm_op_Read.ap_fifo.volatile.floatP" to="tmp_131" fromId="169" toId="70">
</dataflow>
<dataflow id="328" from="strm_in_V" to="tmp_131" fromId="167" toId="70">
</dataflow>
<dataflow id="329" from="_ssdm_op_Read.ap_fifo.volatile.floatP" to="tmp_132" fromId="169" toId="71">
</dataflow>
<dataflow id="330" from="strm_in_V" to="tmp_132" fromId="167" toId="71">
</dataflow>
<dataflow id="331" from="_ssdm_op_Read.ap_fifo.volatile.floatP" to="tmp_133" fromId="169" toId="72">
</dataflow>
<dataflow id="332" from="strm_in_V" to="tmp_133" fromId="167" toId="72">
</dataflow>
<dataflow id="333" from="_ssdm_op_Read.ap_fifo.volatile.floatP" to="tmp_134" fromId="169" toId="73">
</dataflow>
<dataflow id="334" from="strm_in_V" to="tmp_134" fromId="167" toId="73">
</dataflow>
<dataflow id="335" from="tmp_129" to="tmp_i_i_20" fromId="68" toId="74">
</dataflow>
<dataflow id="336" from="tmp_133" to="tmp_i_i_20" fromId="72" toId="74">
</dataflow>
<dataflow id="337" from="tmp_129" to="tmp_i_i_20" fromId="68" toId="75">
</dataflow>
<dataflow id="338" from="tmp_133" to="tmp_i_i_20" fromId="72" toId="75">
</dataflow>
<dataflow id="339" from="tmp_131" to="tmp_3_i_i" fromId="70" toId="76">
</dataflow>
<dataflow id="340" from="tmp_134" to="tmp_3_i_i" fromId="73" toId="76">
</dataflow>
<dataflow id="341" from="tmp_129" to="tmp_i_i_20" fromId="68" toId="77">
</dataflow>
<dataflow id="342" from="tmp_133" to="tmp_i_i_20" fromId="72" toId="77">
</dataflow>
<dataflow id="343" from="tmp_131" to="tmp_3_i_i" fromId="70" toId="78">
</dataflow>
<dataflow id="344" from="tmp_134" to="tmp_3_i_i" fromId="73" toId="78">
</dataflow>
<dataflow id="345" from="tmp_130" to="tmp_i10_i" fromId="69" toId="79">
</dataflow>
<dataflow id="346" from="tmp_133" to="tmp_i10_i" fromId="72" toId="79">
</dataflow>
<dataflow id="347" from="tmp_129" to="tmp_i_i_20" fromId="68" toId="80">
</dataflow>
<dataflow id="348" from="tmp_133" to="tmp_i_i_20" fromId="72" toId="80">
</dataflow>
<dataflow id="349" from="tmp_131" to="tmp_3_i_i" fromId="70" toId="81">
</dataflow>
<dataflow id="350" from="tmp_134" to="tmp_3_i_i" fromId="73" toId="81">
</dataflow>
<dataflow id="351" from="tmp_130" to="tmp_i10_i" fromId="69" toId="82">
</dataflow>
<dataflow id="352" from="tmp_133" to="tmp_i10_i" fromId="72" toId="82">
</dataflow>
<dataflow id="353" from="tmp_132" to="tmp_3_i11_i" fromId="71" toId="83">
</dataflow>
<dataflow id="354" from="tmp_134" to="tmp_3_i11_i" fromId="73" toId="83">
</dataflow>
<dataflow id="355" from="tmp_131" to="tmp_3_i_i" fromId="70" toId="84">
</dataflow>
<dataflow id="356" from="tmp_134" to="tmp_3_i_i" fromId="73" toId="84">
</dataflow>
<dataflow id="357" from="tmp_130" to="tmp_i10_i" fromId="69" toId="85">
</dataflow>
<dataflow id="358" from="tmp_133" to="tmp_i10_i" fromId="72" toId="85">
</dataflow>
<dataflow id="359" from="tmp_132" to="tmp_3_i11_i" fromId="71" toId="86">
</dataflow>
<dataflow id="360" from="tmp_134" to="tmp_3_i11_i" fromId="73" toId="86">
</dataflow>
<dataflow id="361" from="tmp_i_i_20" to="tmp_126" fromId="80" toId="87">
</dataflow>
<dataflow id="362" from="tmp_3_i_i" to="tmp_126" fromId="84" toId="87">
</dataflow>
<dataflow id="363" from="tmp_130" to="tmp_i10_i" fromId="69" toId="88">
</dataflow>
<dataflow id="364" from="tmp_133" to="tmp_i10_i" fromId="72" toId="88">
</dataflow>
<dataflow id="365" from="tmp_132" to="tmp_3_i11_i" fromId="71" toId="89">
</dataflow>
<dataflow id="366" from="tmp_134" to="tmp_3_i11_i" fromId="73" toId="89">
</dataflow>
<dataflow id="367" from="tmp_i_i_20" to="tmp_126" fromId="80" toId="90">
</dataflow>
<dataflow id="368" from="tmp_3_i_i" to="tmp_126" fromId="84" toId="90">
</dataflow>
<dataflow id="369" from="tmp_132" to="tmp_3_i11_i" fromId="71" toId="91">
</dataflow>
<dataflow id="370" from="tmp_134" to="tmp_3_i11_i" fromId="73" toId="91">
</dataflow>
<dataflow id="371" from="tmp_i_i_20" to="tmp_126" fromId="80" toId="92">
</dataflow>
<dataflow id="372" from="tmp_3_i_i" to="tmp_126" fromId="84" toId="92">
</dataflow>
<dataflow id="373" from="tmp_i10_i" to="tmp_127" fromId="88" toId="93">
</dataflow>
<dataflow id="374" from="tmp_3_i11_i" to="tmp_127" fromId="91" toId="93">
</dataflow>
<dataflow id="375" from="tmp_i_i_20" to="tmp_126" fromId="80" toId="94">
</dataflow>
<dataflow id="376" from="tmp_3_i_i" to="tmp_126" fromId="84" toId="94">
</dataflow>
<dataflow id="377" from="tmp_i10_i" to="tmp_127" fromId="88" toId="95">
</dataflow>
<dataflow id="378" from="tmp_3_i11_i" to="tmp_127" fromId="91" toId="95">
</dataflow>
<dataflow id="379" from="tmp_i_i_20" to="tmp_126" fromId="80" toId="96">
</dataflow>
<dataflow id="380" from="tmp_3_i_i" to="tmp_126" fromId="84" toId="96">
</dataflow>
<dataflow id="381" from="tmp_i10_i" to="tmp_127" fromId="88" toId="97">
</dataflow>
<dataflow id="382" from="tmp_3_i11_i" to="tmp_127" fromId="91" toId="97">
</dataflow>
<dataflow id="383" from="tmp_i10_i" to="tmp_127" fromId="88" toId="98">
</dataflow>
<dataflow id="384" from="tmp_3_i11_i" to="tmp_127" fromId="91" toId="98">
</dataflow>
<dataflow id="386" from="_ssdm_op_Write.ap_fifo.volatile.floatP" to="stg_99" fromId="385" toId="99">
</dataflow>
<dataflow id="387" from="strm_out_V" to="stg_99" fromId="168" toId="99">
</dataflow>
<dataflow id="388" from="tmp_126" to="stg_99" fromId="96" toId="99">
</dataflow>
<dataflow id="389" from="tmp_i10_i" to="tmp_127" fromId="88" toId="100">
</dataflow>
<dataflow id="390" from="tmp_3_i11_i" to="tmp_127" fromId="91" toId="100">
</dataflow>
<dataflow id="392" from="_ssdm_op_SpecLoopName" to="stg_101" fromId="391" toId="101">
</dataflow>
<dataflow id="394" from="L_svd_calc_off_c_str" to="stg_101" fromId="393" toId="101">
</dataflow>
<dataflow id="396" from="_ssdm_op_SpecLoopTripCount" to="empty_19" fromId="395" toId="102">
</dataflow>
<dataflow id="398" from="stg_397" to="empty_19" fromId="397" toId="102">
</dataflow>
<dataflow id="399" from="stg_397" to="empty_19" fromId="397" toId="102">
</dataflow>
<dataflow id="400" from="stg_397" to="empty_19" fromId="397" toId="102">
</dataflow>
<dataflow id="401" from="_ssdm_op_SpecLoopName" to="stg_103" fromId="391" toId="103">
</dataflow>
<dataflow id="403" from="p_str1810" to="stg_103" fromId="402" toId="103">
</dataflow>
<dataflow id="405" from="_ssdm_op_SpecRegionBegin" to="tmp_32_i" fromId="404" toId="104">
</dataflow>
<dataflow id="406" from="p_str1810" to="tmp_32_i" fromId="402" toId="104">
</dataflow>
<dataflow id="408" from="_ssdm_op_SpecPipeline" to="stg_105" fromId="407" toId="105">
</dataflow>
<dataflow id="410" from="stg_409" to="stg_105" fromId="409" toId="105">
</dataflow>
<dataflow id="411" from="stg_280" to="stg_105" fromId="280" toId="105">
</dataflow>
<dataflow id="412" from="stg_280" to="stg_105" fromId="280" toId="105">
</dataflow>
<dataflow id="413" from="stg_207" to="stg_105" fromId="207" toId="105">
</dataflow>
<dataflow id="415" from="p_str1806" to="stg_105" fromId="414" toId="105">
</dataflow>
<dataflow id="416" from="_ssdm_op_Write.ap_fifo.volatile.floatP" to="stg_106" fromId="385" toId="106">
</dataflow>
<dataflow id="417" from="strm_out_V" to="stg_106" fromId="168" toId="106">
</dataflow>
<dataflow id="418" from="tmp_127" to="stg_106" fromId="100" toId="106">
</dataflow>
<dataflow id="420" from="_ssdm_op_SpecRegionEnd" to="empty_21" fromId="419" toId="107">
</dataflow>
<dataflow id="421" from="p_str1810" to="empty_21" fromId="402" toId="107">
</dataflow>
<dataflow id="422" from="tmp_32_i" to="empty_21" fromId="104" toId="107">
</dataflow>
<dataflow id="423" from="dut_update_off_diag_r" to="stg_109" fromId="297" toId="109">
</dataflow>
<dataflow id="424" from="strm_in_V" to="stg_109" fromId="167" toId="109">
</dataflow>
<dataflow id="425" from="strm_out_V" to="stg_109" fromId="168" toId="109">
</dataflow>
<dataflow id="426" from="dut_calc_svd" to="stg_111" fromId="301" toId="111">
</dataflow>
<dataflow id="427" from="strm_in_V" to="stg_111" fromId="167" toId="111">
</dataflow>
<dataflow id="428" from="strm_out_V" to="stg_111" fromId="168" toId="111">
</dataflow>
<dataflow id="429" from="isNeg" to="stg_2" fromId="32" toId="2">
</dataflow>
<dataflow id="430" from="p_Result_s" to="stg_2" fromId="27" toId="2">
</dataflow>
<dataflow id="431" from="p_Val2_5" to="stg_2" fromId="53" toId="2">
</dataflow>
<dataflow id="432" from="p_Val2_5" to="stg_3" fromId="53" toId="3">
</dataflow>
<dataflow id="433" from="exitcond_flatten" to="stg_5" fromId="65" toId="5">
</dataflow>
<dataflow id="434" from="exitcond_flatten" to="stg_6" fromId="65" toId="6">
</dataflow>
<dataflow id="435" from="exitcond_flatten" to="stg_7" fromId="65" toId="7">
</dataflow>
<dataflow id="436" from="exitcond_flatten" to="stg_8" fromId="65" toId="8">
</dataflow>
<dataflow id="437" from="exitcond_flatten" to="stg_9" fromId="65" toId="9">
</dataflow>
<dataflow id="438" from="exitcond_flatten" to="stg_10" fromId="65" toId="10">
</dataflow>
<dataflow id="439" from="exitcond_flatten" to="stg_11" fromId="65" toId="11">
</dataflow>
<dataflow id="440" from="exitcond_flatten" to="stg_12" fromId="65" toId="12">
</dataflow>
<dataflow id="441" from="exitcond_flatten" to="stg_13" fromId="65" toId="13">
</dataflow>
<dataflow id="442" from="exitcond_flatten" to="stg_14" fromId="65" toId="14">
</dataflow>
<dataflow id="443" from="exitcond_flatten" to="stg_15" fromId="65" toId="15">
</dataflow>
<dataflow id="444" from="exitcond_flatten" to="stg_16" fromId="65" toId="16">
</dataflow>
<dataflow id="445" from="exitcond_flatten" to="stg_17" fromId="65" toId="17">
</dataflow>
<dataflow id="446" from="exitcond_flatten" to="stg_18" fromId="65" toId="18">
</dataflow>
<dataflow id="447" from="exitcond_flatten" to="stg_19" fromId="65" toId="19">
</dataflow>
<dataflow id="448" from="exitcond_flatten" to="stg_20" fromId="65" toId="20">
</dataflow>
<dataflow id="449" from="exitcond_flatten" to="stg_21" fromId="65" toId="21">
</dataflow>
<dataflow id="450" from="exitcond_flatten" to="stg_22" fromId="65" toId="22">
</dataflow>
<dataflow id="451" from="p_Val2_5" to="stg_23" fromId="53" toId="23">
</dataflow>
<dataflow id="452" from="exitcond_flatten" to="stg_4" fromId="65" toId="4">
</dataflow>
<dataflow id="453" from="p_Val2_5" to="stg_4" fromId="53" toId="4">
</dataflow>
<dataflow id="454" from="p_Val2_5" to="stg_5" fromId="53" toId="5">
</dataflow>
<dataflow id="455" from="p_Val2_5" to="stg_6" fromId="53" toId="6">
</dataflow>
<dataflow id="456" from="p_Val2_5" to="stg_7" fromId="53" toId="7">
</dataflow>
<dataflow id="457" from="p_Val2_5" to="stg_8" fromId="53" toId="8">
</dataflow>
<dataflow id="458" from="p_Val2_5" to="stg_9" fromId="53" toId="9">
</dataflow>
<dataflow id="459" from="p_Val2_5" to="stg_10" fromId="53" toId="10">
</dataflow>
<dataflow id="460" from="p_Val2_5" to="stg_11" fromId="53" toId="11">
</dataflow>
<dataflow id="461" from="p_Val2_5" to="stg_12" fromId="53" toId="12">
</dataflow>
<dataflow id="462" from="p_Val2_5" to="stg_13" fromId="53" toId="13">
</dataflow>
<dataflow id="463" from="p_Val2_5" to="stg_14" fromId="53" toId="14">
</dataflow>
<dataflow id="464" from="p_Val2_5" to="stg_15" fromId="53" toId="15">
</dataflow>
<dataflow id="465" from="p_Val2_5" to="stg_16" fromId="53" toId="16">
</dataflow>
<dataflow id="466" from="p_Val2_5" to="stg_17" fromId="53" toId="17">
</dataflow>
<dataflow id="467" from="p_Val2_5" to="stg_18" fromId="53" toId="18">
</dataflow>
<dataflow id="468" from="p_Val2_5" to="stg_19" fromId="53" toId="19">
</dataflow>
<dataflow id="469" from="p_Val2_5" to="stg_20" fromId="53" toId="20">
</dataflow>
<dataflow id="470" from="p_Val2_5" to="stg_21" fromId="53" toId="21">
</dataflow>
<dataflow id="471" from="p_Val2_5" to="stg_22" fromId="53" toId="22">
</dataflow>
</dataflows>


</stg>
